module_env/__init__.py
module_env/module_env.py
module_env/py.typed
module_env-1.1.2.dist-info/LICENSE
module_env-1.1.2.dist-info/METADATA
module_env-1.1.2.dist-info/WHEEL
module_env-1.1.2.dist-info/top_level.txt
module_env-1.1.2.dist-info/RECORD
