Metadata-Version: 2.1
Name: module_env
Version: 1.1.2
Summary: Context manage-able module-environments for python!
License: GPLv3
Project-URL: Homepage, https://github.com/zwimer/module_env
Classifier: Programming Language :: Python :: 3
Classifier: Programming Language :: Python :: 3.10
Requires-Python: >=3.10
License-File: LICENSE
